{"_default": {"1": {"first_name": "Ana", "last_name": "Kova\u010d", "age": 24, "experience": "3_years", "split": "push_pull_legs", "gym_name": "FitLine", "location": "Ljubljana", "password": "ana123", "contact": "041 111 222"}, "2": {"first_name": "Luka", "last_name": "Zajc", "age": 28, "experience": "3_years", "split": "push_pull_legs", "gym_name": "MuscleZone", "location": "Koper", "password": "luka123", "contact": "041 444 555"}, "3": {"first_name": "Eva", "last_name": "Petek", "age": 26, "experience": "2_years", "split": "full_body", "gym_name": "IronFit", "location": "Nova Gorica", "password": "eva123", "contact": "041 555 666"}, "4": {"first_name": "Tina", "last_name": "Horvat", "age": 23, "experience": "1_year", "split": "push_pull_legs", "gym_name": "PowerGym", "location": "Celje", "password": "tina123", "contact": "041 555 632"}, "5": {"first_name": "\u017dak", "last_name": "Oblak", "age": 17, "experience": "2_years", "split": "push_pull_legs", "gym_name": "topfitnes", "location": "Ljubljana", "password": "\u017eak123", "contact": "070554763"}, "6": {"first_name": "Marko", "last_name": "Kralj", "age": 17, "experience": "za\u010detnik", "split": "push_pull_legs", "gym_name": "BodyZone", "location": "Celje", "password": "test123", "contact": "041 250126"}, "7": {"first_name": "Nika", "last_name": "Kova\u010d", "age": 29, "experience": "napreden", "split": "bro_split", "gym_name": "TopFitnes", "location": "Ljubljana", "password": "test123", "contact": "041 915057"}, "8": {"first_name": "Marko", "last_name": "Vidmar", "age": 18, "experience": "napreden", "split": "push_pull_legs", "gym_name": "GymX", "location": "Maribor", "password": "test123", "contact": "041 571865"}, "9": {"first_name": "Marko", "last_name": "Furlan", "age": 29, "experience": "srednji", "split": "push_pull_legs", "gym_name": "GymX", "location": "Maribor", "password": "test123", "contact": "041 556414"}, "10": {"first_name": "Ana", "last_name": "Bla\u017ei\u010d", "age": 29, "experience": "za\u010detnik", "split": "bro_split", "gym_name": "PowerGym", "location": "Koper", "password": "test123", "contact": "041 223261"}, "11": {"first_name": "Eva", "last_name": "Koren", "age": 23, "experience": "za\u010detnik", "split": "push_pull_legs", "gym_name": "TopFitnes", "location": "Ljubljana", "password": "test123", "contact": "041 392414"}, "12": {"first_name": "Tina", "last_name": "Vidmar", "age": 18, "experience": "srednji", "split": "full_body", "gym_name": "TopFitnes", "location": "Ljubljana", "password": "test123", "contact": "041 295986"}, "13": {"first_name": "\u017dan", "last_name": "Bla\u017ei\u010d", "age": 23, "experience": "srednji", "split": "bro_split", "gym_name": "TopFitnes", "location": "Ljubljana", "password": "test123", "contact": "041 112057"}, "14": {"first_name": "Marko", "last_name": "Bla\u017ei\u010d", "age": 29, "experience": "napreden", "split": "push_pull_legs", "gym_name": "BodyZone", "location": "Celje", "password": "test123", "contact": "041 866115"}, "15": {"first_name": "David", "last_name": "Bla\u017ei\u010d", "age": 17, "experience": "srednji", "split": "bro_split", "gym_name": "PowerGym", "location": "Koper", "password": "test123", "contact": "041 782849"}, "16": {"first_name": "Eva", "last_name": "Zupan", "age": 18, "experience": "napreden", "split": "push_pull_legs", "gym_name": "FitZone", "location": "Ljubljana", "password": "test123", "contact": "041 537731"}, "17": {"first_name": "Marko", "last_name": "Vidmar", "age": 19, "experience": "za\u010detnik", "split": "bro_split", "gym_name": "GymX", "location": "Maribor", "password": "test123", "contact": "041 341809"}, "18": {"first_name": "Marko", "last_name": "Koren", "age": 23, "experience": "za\u010detnik", "split": "full_body", "gym_name": "BodyZone", "location": "Celje", "password": "test123", "contact": "041 363032"}, "19": {"first_name": "Luka", "last_name": "Vidmar", "age": 25, "experience": "napreden", "split": "full_body", "gym_name": "GymX", "location": "Maribor", "password": "test123", "contact": "041 735809"}, "20": {"first_name": "Tina", "last_name": "Novak", "age": 17, "experience": "srednji", "split": "full_body", "gym_name": "FitZone", "location": "Ljubljana", "password": "test123", "contact": "041 669818"}, "21": {"first_name": "Nika", "last_name": "Zupan", "age": 23, "experience": "napreden", "split": "push_pull_legs", "gym_name": "TopFitnes", "location": "Ljubljana", "password": "test123", "contact": "041 862982"}, "22": {"first_name": "David", "last_name": "Horvat", "age": 16, "experience": "srednji", "split": "full_body", "gym_name": "FitZone", "location": "Ljubljana", "password": "test123", "contact": "041 695684"}, "23": {"first_name": "Eva", "last_name": "Bla\u017ei\u010d", "age": 25, "experience": "napreden", "split": "push_pull_legs", "gym_name": "GymX", "location": "Maribor", "password": "test123", "contact": "041 995798"}, "24": {"first_name": "David", "last_name": "Koren", "age": 23, "experience": "za\u010detnik", "split": "full_body", "gym_name": "GymX", "location": "Maribor", "password": "test123", "contact": "041 835725"}, "25": {"first_name": "Tina", "last_name": "Poto\u010dnik", "age": 23, "experience": "napreden", "split": "full_body", "gym_name": "BodyZone", "location": "Celje", "password": "test123", "contact": "041 425431"}, "26": {"first_name": "luka", "last_name": "jeli\u0107", "age": 17, "experience": "1_year", "split": "bro_split", "gym_name": "megacenter", "location": "Kranj", "password": "luka1234", "contact": "040350312"}}}